{
  "$schema": "https://turbo.build/schema.json",
  "ui": "tui",
  "tasks": {
    "build": {
      "dependsOn": ["^build"],
      "inputs": ["$TURBO_DEFAULT$", ".env*"],
      "outputs": ["dist/**", ".next/**"],
      "env": [
        "DATABASE_URL",
        "DATABASE_URL_DIRECT",
        "DATABASE_URL_LOCAL",
        "DATABASE_URL_UNPOOLED",
        "NEON_API_KEY",
        "BETTER_AUTH_SECRET",
        "BETTER_AUTH_URL",
        "GOOGLE_GENERATIVE_AI_API_KEY",
        "CORS_ORIGIN",
        "VERCEL_URL",
        "VERCEL_ENV",
        "NODE_ENV"
      ]
    },
    "lint": {
      "dependsOn": ["^lint"]
    },
    "check-types": {
      "dependsOn": ["^check-types"]
    },
    "dev": {
      "cache": false,
      "persistent": true
    },
    "db:push": {
      "cache": false
    },
    "db:studio": {
      "cache": false,
      "persistent": true
    },
    "db:migrate": {
      "cache": false
    },
    "db:generate": {
      "cache": false
    }
  }
}
